Metadata-Version: 2.1
Name: r-quests
Version: 0.0.1
Summary: POC for homoglyph attacks against package managers.
Home-page: https://github.com/s0md3v/rеquests
Download-URL: https://github.com/s0md3v/rеquests/archive/v0.0.1.zip
Author: s0md3v
License: Apache-2.0 License
Classifier: Topic :: Security
Classifier: Operating System :: OS Independent
Classifier: License :: OSI Approved :: Apache Software License
Classifier: Programming Language :: Python :: 3
License-File: LICENSE
